setup.cfg
setup.py
demopan/__init__.py
demopan/__main__.py
demopan.egg-info/PKG-INFO
demopan.egg-info/SOURCES.txt
demopan.egg-info/dependency_links.txt
demopan.egg-info/entry_points.txt
demopan.egg-info/requires.txt
demopan.egg-info/top_level.txt