Metadata-Version: 1.1
Name: demopan
Version: 0.4
Summary: A cross-platform Source demo organiser
Home-page: https://github.com/vixus0/demopan
Author: vixus0
Author-email: vixus0@gmail.com
License: WTFPL
Download-URL: https://github.com/vixus0/demopan/tarball/0.4
Keywords: recording demo games steam
Platform: UNKNOWN
Classifier: Development Status :: 3 - Alpha
Classifier: Intended Audience :: End Users/Desktop
Classifier: Topic :: Games/Entertainment
Classifier: License :: Freely Distributable
Classifier: Programming Language :: Python :: 2.7
Classifier: Programming Language :: Python :: 3.4
